{"id":"a0cou","label":"","pages":[{"id":"index","title":"Home Page","content":[{"id":"y4sx5","width":"contained","columns":[{"id":"flup0","size":"w-full","rows":[{"type":"component","id":"jovso","symbolID":"56iti","value":{"raw":{"html":"<div class=\"bg-white py-8 map\">\n    <div class=\"py-8 text-center text-gray-900 container\">\n        <h3 class=\"text-2xl md:text-3xl font-bold leading-tight\">{{title}}</h3>\n        <p class=\"text-xl\">{{subtitle}}</p>\n    </div>\n    <div class=\"grid md:grid-cols-2 lg:grid-cols-3 gap-6 lg:gap-12 pb-16 container\">\n        {{#each items}}\n            <a data-aos=\"fade-up\" data-aos-duration=\"1000\" href=\"{{url}}\" class=\"item text-white shadow-xl relative pt-8 pb-8 w-full bg-black\">\n            \t{{#if image.url}}\n            \t\t<img class=\"opacity-50 absolute left-0 top-0 w-full h-full object-cover\" src=\"{{image.url}}\" alt=\"{{image.alt}}\">\n                {{/if}}\n                <div class=\"pl-8 pr-4 flex flex-col font-bold leading-tight text-xl relative z-10\">\n                \t{{#if description}}\n            \t\t\t<div class=\"description text-sm font-semibold py-8 opacity-0 transition-opacity duration-200\">{{{description}}}</div>\n                    {{/if}}\n                    <div class=\"flex justify-between\">\n                        <div>\n                        \t<p>{{title}}</p>\n                        \t<p class=\"font-medium text-sm\">{{subtitle}}</p>\n                        </div>\n                        <svg class=\"w-6 h-6\" fill=\"currentColor\" viewBox=\"0 0 20 20\" xmlns=\"http://www.w3.org/2000/svg\"><path fill-rule=\"evenodd\" d=\"M7.293 14.707a1 1 0 010-1.414L10.586 10 7.293 6.707a1 1 0 011.414-1.414l4 4a1 1 0 010 1.414l-4 4a1 1 0 01-1.414 0z\" clip-rule=\"evenodd\"></path></svg>\n                    </div>\n                </div>\n            </a>\n        {{/each}}\n    </div>\n</div>\n<link href=\"https://unpkg.com/aos@2.3.1/dist/aos.css\" rel=\"stylesheet\">","css":".item:hover .description, .item:focus .description {\n\t@apply opacity-100;\n}","js":"import AOS from 'aos'\nAOS.init()","fields":[{"id":"hrmxk","key":"title","label":"Title","value":"The Maadi Guide","type":"text","fields":[]},{"id":"qayiv","key":"subtitle","label":"Subtitle","value":"The best places to eat in Maadi, Egypt","type":"text","fields":[]},{"id":"jtnwe","key":"items","label":"Items","value":[{"title":"Tomato","description":"<p>Porta nibh venenatis cras sed felis. Amet mattis vulputate enim nulla aliquet porttitor lacus luctus. Viverra ipsum nunc aliquet bibendum enim. </p>","url":"#","image":{"alt":"mountains","url":"https://images.unsplash.com/photo-1498654896293-37aacf113fd9?ixid=MXwxMjA3fDB8MHxwaG90by1wYWdlfHx8fGVufDB8fHw%3D&ixlib=rb-1.2.1&auto=format&fit=crop&w=1950&q=80","size":null},"subtitle":"Korean"},{"title":"What the Crust","description":"<p>Orci sagittis eu volutpat odio facilisis mauris sit amet. Scelerisque viverra mauris in aliquam sem fringilla ut. Urna condimentum mattis pellentesque id nibh tortor id aliquet.</p>","url":"#","image":{"alt":"pizza","url":"https://images.unsplash.com/photo-1528137871618-79d2761e3fd5?ixid=MXwxMjA3fDB8MHxwaG90by1wYWdlfHx8fGVufDB8fHw%3D&ixlib=rb-1.2.1&auto=format&fit=crop&w=1950&q=80","size":null},"subtitle":"Pizza"},{"title":"Thai Baitong","description":"<p>Viverra ipsum nunc aliquet bibendum enim. Orci sagittis eu volutpat odio facilisis mauris sit amet. Scelerisque viverra mauris in aliquam sem fringilla ut. </p>","url":"#","image":{"alt":"thai food","url":"https://images.unsplash.com/photo-1567982047351-76b6f93e38ee?ixid=MXwxMjA3fDB8MHxwaG90by1wYWdlfHx8fGVufDB8fHw%3D&ixlib=rb-1.2.1&auto=format&fit=crop&w=1950&q=80","size":null},"subtitle":"Thai"}],"type":"repeater","fields":[{"id":"vxggv","key":"title","label":"Title","value":"","type":"text"},{"id":"mvomp","key":"description","label":"Description","value":"","type":"content"},{"id":"3llpc","key":"url","label":"URL","value":"","type":"url"},{"id":"quqhg","key":"image","label":"Image","value":"","type":"image"},{"id":"lyhoq","key":"subtitle","label":"Subtitle","value":"","type":"text"}]}]},"final":{"html":"<div class=\"bg-white py-8 map\">\n    <div class=\"py-8 text-center text-gray-900 container\">\n        <h3 class=\"text-2xl md:text-3xl font-bold leading-tight\">The Maadi Guide</h3>\n        <p class=\"text-xl\">The best places to eat in Maadi, Egypt</p>\n    </div>\n    <div class=\"grid md:grid-cols-2 lg:grid-cols-3 gap-6 lg:gap-12 pb-16 container\">\n            <a data-aos=\"fade-up\" data-aos-duration=\"1000\" href=\"#\" class=\"item text-white shadow-xl relative pt-8 pb-8 w-full bg-black\">\n            \t\t<img class=\"opacity-50 absolute left-0 top-0 w-full h-full object-cover\" src=\"https://images.unsplash.com/photo-1498654896293-37aacf113fd9?ixid&#x3D;MXwxMjA3fDB8MHxwaG90by1wYWdlfHx8fGVufDB8fHw%3D&amp;ixlib&#x3D;rb-1.2.1&amp;auto&#x3D;format&amp;fit&#x3D;crop&amp;w&#x3D;1950&amp;q&#x3D;80\" alt=\"mountains\">\n                <div class=\"pl-8 pr-4 flex flex-col font-bold leading-tight text-xl relative z-10\">\n            \t\t\t<div class=\"description text-sm font-semibold py-8 opacity-0 transition-opacity duration-200\"><p>Porta nibh venenatis cras sed felis. Amet mattis vulputate enim nulla aliquet porttitor lacus luctus. Viverra ipsum nunc aliquet bibendum enim. </p></div>\n                    <div class=\"flex justify-between\">\n                        <div>\n                        \t<p>Tomato</p>\n                        \t<p class=\"font-medium text-sm\">Korean</p>\n                        </div>\n                        <svg class=\"w-6 h-6\" fill=\"currentColor\" viewBox=\"0 0 20 20\" xmlns=\"http://www.w3.org/2000/svg\"><path fill-rule=\"evenodd\" d=\"M7.293 14.707a1 1 0 010-1.414L10.586 10 7.293 6.707a1 1 0 011.414-1.414l4 4a1 1 0 010 1.414l-4 4a1 1 0 01-1.414 0z\" clip-rule=\"evenodd\"></path></svg>\n                    </div>\n                </div>\n            </a>\n            <a data-aos=\"fade-up\" data-aos-duration=\"1000\" href=\"#\" class=\"item text-white shadow-xl relative pt-8 pb-8 w-full bg-black\">\n            \t\t<img class=\"opacity-50 absolute left-0 top-0 w-full h-full object-cover\" src=\"https://images.unsplash.com/photo-1528137871618-79d2761e3fd5?ixid&#x3D;MXwxMjA3fDB8MHxwaG90by1wYWdlfHx8fGVufDB8fHw%3D&amp;ixlib&#x3D;rb-1.2.1&amp;auto&#x3D;format&amp;fit&#x3D;crop&amp;w&#x3D;1950&amp;q&#x3D;80\" alt=\"pizza\">\n                <div class=\"pl-8 pr-4 flex flex-col font-bold leading-tight text-xl relative z-10\">\n            \t\t\t<div class=\"description text-sm font-semibold py-8 opacity-0 transition-opacity duration-200\"><p>Orci sagittis eu volutpat odio facilisis mauris sit amet. Scelerisque viverra mauris in aliquam sem fringilla ut. Urna condimentum mattis pellentesque id nibh tortor id aliquet.</p></div>\n                    <div class=\"flex justify-between\">\n                        <div>\n                        \t<p>What the Crust</p>\n                        \t<p class=\"font-medium text-sm\">Pizza</p>\n                        </div>\n                        <svg class=\"w-6 h-6\" fill=\"currentColor\" viewBox=\"0 0 20 20\" xmlns=\"http://www.w3.org/2000/svg\"><path fill-rule=\"evenodd\" d=\"M7.293 14.707a1 1 0 010-1.414L10.586 10 7.293 6.707a1 1 0 011.414-1.414l4 4a1 1 0 010 1.414l-4 4a1 1 0 01-1.414 0z\" clip-rule=\"evenodd\"></path></svg>\n                    </div>\n                </div>\n            </a>\n            <a data-aos=\"fade-up\" data-aos-duration=\"1000\" href=\"#\" class=\"item text-white shadow-xl relative pt-8 pb-8 w-full bg-black\">\n            \t\t<img class=\"opacity-50 absolute left-0 top-0 w-full h-full object-cover\" src=\"https://images.unsplash.com/photo-1567982047351-76b6f93e38ee?ixid&#x3D;MXwxMjA3fDB8MHxwaG90by1wYWdlfHx8fGVufDB8fHw%3D&amp;ixlib&#x3D;rb-1.2.1&amp;auto&#x3D;format&amp;fit&#x3D;crop&amp;w&#x3D;1950&amp;q&#x3D;80\" alt=\"thai food\">\n                <div class=\"pl-8 pr-4 flex flex-col font-bold leading-tight text-xl relative z-10\">\n            \t\t\t<div class=\"description text-sm font-semibold py-8 opacity-0 transition-opacity duration-200\"><p>Viverra ipsum nunc aliquet bibendum enim. Orci sagittis eu volutpat odio facilisis mauris sit amet. Scelerisque viverra mauris in aliquam sem fringilla ut. </p></div>\n                    <div class=\"flex justify-between\">\n                        <div>\n                        \t<p>Thai Baitong</p>\n                        \t<p class=\"font-medium text-sm\">Thai</p>\n                        </div>\n                        <svg class=\"w-6 h-6\" fill=\"currentColor\" viewBox=\"0 0 20 20\" xmlns=\"http://www.w3.org/2000/svg\"><path fill-rule=\"evenodd\" d=\"M7.293 14.707a1 1 0 010-1.414L10.586 10 7.293 6.707a1 1 0 011.414-1.414l4 4a1 1 0 010 1.414l-4 4a1 1 0 01-1.414 0z\" clip-rule=\"evenodd\"></path></svg>\n                    </div>\n                </div>\n            </a>\n    </div>\n</div>\n<link href=\"https://unpkg.com/aos@2.3.1/dist/aos.css\" rel=\"stylesheet\">","css":"#component-td4zm .item:hover .description, #component-td4zm .item:focus .description {\n    opacity: 1;\n  }","js":"\n      const primo = {\n        id: 'jovso',\n        data: {\"title\":\"The Maadi Guide\",\"subtitle\":\"The best places to eat in Maadi, Egypt\",\"items\":[{\"title\":\"Tomato\",\"description\":\"<p>Porta nibh venenatis cras sed felis. Amet mattis vulputate enim nulla aliquet porttitor lacus luctus. Viverra ipsum nunc aliquet bibendum enim. </p>\",\"url\":\"#\",\"image\":{\"alt\":\"mountains\",\"url\":\"https://images.unsplash.com/photo-1498654896293-37aacf113fd9?ixid=MXwxMjA3fDB8MHxwaG90by1wYWdlfHx8fGVufDB8fHw%3D&ixlib=rb-1.2.1&auto=format&fit=crop&w=1950&q=80\",\"size\":null},\"subtitle\":\"Korean\"},{\"title\":\"What the Crust\",\"description\":\"<p>Orci sagittis eu volutpat odio facilisis mauris sit amet. Scelerisque viverra mauris in aliquam sem fringilla ut. Urna condimentum mattis pellentesque id nibh tortor id aliquet.</p>\",\"url\":\"#\",\"image\":{\"alt\":\"pizza\",\"url\":\"https://images.unsplash.com/photo-1528137871618-79d2761e3fd5?ixid=MXwxMjA3fDB8MHxwaG90by1wYWdlfHx8fGVufDB8fHw%3D&ixlib=rb-1.2.1&auto=format&fit=crop&w=1950&q=80\",\"size\":null},\"subtitle\":\"Pizza\"},{\"title\":\"Thai Baitong\",\"description\":\"<p>Viverra ipsum nunc aliquet bibendum enim. Orci sagittis eu volutpat odio facilisis mauris sit amet. Scelerisque viverra mauris in aliquam sem fringilla ut. </p>\",\"url\":\"#\",\"image\":{\"alt\":\"thai food\",\"url\":\"https://images.unsplash.com/photo-1567982047351-76b6f93e38ee?ixid=MXwxMjA3fDB8MHxwaG90by1wYWdlfHx8fGVufDB8fHw%3D&ixlib=rb-1.2.1&auto=format&fit=crop&w=1950&q=80\",\"size\":null},\"subtitle\":\"Thai\"}],\"id\":\"jovso\"},\n        fields: [{\"id\":\"hrmxk\",\"key\":\"title\",\"label\":\"Title\",\"value\":\"The Maadi Guide\",\"type\":\"text\",\"fields\":[]},{\"id\":\"qayiv\",\"key\":\"subtitle\",\"label\":\"Subtitle\",\"value\":\"The best places to eat in Maadi, Egypt\",\"type\":\"text\",\"fields\":[]},{\"id\":\"jtnwe\",\"key\":\"items\",\"label\":\"Items\",\"value\":[{\"title\":\"Tomato\",\"description\":\"<p>Porta nibh venenatis cras sed felis. Amet mattis vulputate enim nulla aliquet porttitor lacus luctus. Viverra ipsum nunc aliquet bibendum enim. </p>\",\"url\":\"#\",\"image\":{\"alt\":\"mountains\",\"url\":\"https://images.unsplash.com/photo-1498654896293-37aacf113fd9?ixid=MXwxMjA3fDB8MHxwaG90by1wYWdlfHx8fGVufDB8fHw%3D&ixlib=rb-1.2.1&auto=format&fit=crop&w=1950&q=80\",\"size\":null},\"subtitle\":\"Korean\"},{\"title\":\"What the Crust\",\"description\":\"<p>Orci sagittis eu volutpat odio facilisis mauris sit amet. Scelerisque viverra mauris in aliquam sem fringilla ut. Urna condimentum mattis pellentesque id nibh tortor id aliquet.</p>\",\"url\":\"#\",\"image\":{\"alt\":\"pizza\",\"url\":\"https://images.unsplash.com/photo-1528137871618-79d2761e3fd5?ixid=MXwxMjA3fDB8MHxwaG90by1wYWdlfHx8fGVufDB8fHw%3D&ixlib=rb-1.2.1&auto=format&fit=crop&w=1950&q=80\",\"size\":null},\"subtitle\":\"Pizza\"},{\"title\":\"Thai Baitong\",\"description\":\"<p>Viverra ipsum nunc aliquet bibendum enim. Orci sagittis eu volutpat odio facilisis mauris sit amet. Scelerisque viverra mauris in aliquam sem fringilla ut. </p>\",\"url\":\"#\",\"image\":{\"alt\":\"thai food\",\"url\":\"https://images.unsplash.com/photo-1567982047351-76b6f93e38ee?ixid=MXwxMjA3fDB8MHxwaG90by1wYWdlfHx8fGVufDB8fHw%3D&ixlib=rb-1.2.1&auto=format&fit=crop&w=1950&q=80\",\"size\":null},\"subtitle\":\"Thai\"}],\"type\":\"repeater\",\"fields\":[{\"id\":\"vxggv\",\"key\":\"title\",\"label\":\"Title\",\"value\":\"\",\"type\":\"text\"},{\"id\":\"mvomp\",\"key\":\"description\",\"label\":\"Description\",\"value\":\"\",\"type\":\"content\"},{\"id\":\"3llpc\",\"key\":\"url\",\"label\":\"URL\",\"value\":\"\",\"type\":\"url\"},{\"id\":\"quqhg\",\"key\":\"image\",\"label\":\"Image\",\"value\":\"\",\"type\":\"image\"},{\"id\":\"lyhoq\",\"key\":\"subtitle\",\"label\":\"Subtitle\",\"value\":\"\",\"type\":\"text\"}]}]\n      }\n      // turn [import _ from 'lodash'] into [import _ from 'https://cdn.skypack.dev/lodash'];\n      import AOS from 'https://cdn.skypack.dev/aos'\nAOS.init() \n    "}}}]}]}],"styles":{"raw":"","final":"","tailwind":"{\n  theme: {\n    container: {\n      center: true,\n      padding: '2rem'\n    }\n  },\n  variants: {}\n}"},"wrapper":{"head":{"raw":"","final":""},"below":{"raw":"","final":""}},"fields":[]}],"styles":{"raw":"/* Default content styles */\n\n.primo-copy {\n  @apply text-lg text-gray-700;\n  h1 {\n    @apply text-3xl font-medium;\n  }\n  h2 {\n    @apply text-2xl font-medium;\n  }\n  ol {\n    @apply list-decimal;\n  }\n  ul {\n    @apply list-disc list-inside;\n    p {\n        @apply inline;\n    }\n  } \n  ol {\n    @apply list-decimal list-inside;\n  } \n  a {\n    @apply text-blue-600 underline;\n  }\n  blockquote {\n      @apply shadow-md p-6;\n  }\n  mark {\n    @apply text-gray-900 bg-yellow-200;\n  }\n  \n  @screen lg {\n    h1 {\n      @apply text-5xl;\n    }\n    h2 {\n      @apply text-4xl;\n    }\n  }\n}","final":"/* Default content styles */\n\n.primo-copy {\n  font-size: 1.125rem;\n  --text-opacity: 1;\n  color: #374151;\n  color: rgba(55, 65, 81, var(--text-opacity));\n}\n\n.primo-copy h1 {\n    font-size: 1.875rem;\n    font-weight: 500;\n  }\n\n.primo-copy h2 {\n    font-size: 1.5rem;\n    font-weight: 500;\n  }\n\n.primo-copy ol {\n    list-style-type: decimal;\n  }\n\n.primo-copy ul {\n    list-style-type: disc;\n    list-style-position: inside;\n  }\n\n.primo-copy ul p {\n      display: inline;\n    }\n\n.primo-copy ol {\n    list-style-type: decimal;\n    list-style-position: inside;\n  }\n\n.primo-copy a {\n    --text-opacity: 1;\n    color: #1c64f2;\n    color: rgba(28, 100, 242, var(--text-opacity));\n    text-decoration: underline;\n  }\n\n.primo-copy blockquote {\n    box-shadow: 0 4px 6px -1px rgba(0, 0, 0, 0.1), 0 2px 4px -1px rgba(0, 0, 0, 0.06);\n    padding: 1.5rem;\n  }\n\n.primo-copy mark {\n    --text-opacity: 1;\n    color: #161e2e;\n    color: rgba(22, 30, 46, var(--text-opacity));\n    --bg-opacity: 1;\n    background-color: #fce96a;\n    background-color: rgba(252, 233, 106, var(--bg-opacity));\n  }\n\n@media (min-width: 1024px) {\n  .primo-copy h1 {\n    font-size: 3rem;\n  }\n\n  .primo-copy h2 {\n    font-size: 2.25rem;\n  }\n}\n  ","tailwind":"{\n  theme: {\n    container: {\n      center: true,\n      padding: '2rem'\n    }\n  },\n  variants: {}\n}"},"wrapper":{"head":{"raw":"","final":""},"below":{"raw":"","final":""}},"fields":[],"symbols":[{"type":"symbol","id":"56iti","value":{"raw":{"html":"<div class=\"bg-white py-8 map\">\n    <div class=\"py-8 text-center text-gray-900 container\">\n        <h3 class=\"text-2xl md:text-3xl font-bold leading-tight\">{{title}}</h3>\n        <p class=\"text-xl\">{{subtitle}}</p>\n    </div>\n    <div class=\"grid md:grid-cols-2 lg:grid-cols-3 gap-6 lg:gap-12 pb-16 container\">\n        {{#each items}}\n            <a data-aos=\"fade-up\" data-aos-duration=\"1000\" href=\"{{url}}\" class=\"item text-white shadow-xl relative pt-8 pb-8 w-full bg-black\">\n            \t{{#if image.url}}\n            \t\t<img class=\"opacity-50 absolute left-0 top-0 w-full h-full object-cover\" src=\"{{image.url}}\" alt=\"{{image.alt}}\">\n                {{/if}}\n                <div class=\"pl-8 pr-4 flex flex-col font-bold leading-tight text-xl relative z-10\">\n                \t{{#if description}}\n            \t\t\t<div class=\"description text-sm font-semibold py-8 opacity-0 transition-opacity duration-200\">{{{description}}}</div>\n                    {{/if}}\n                    <div class=\"flex justify-between\">\n                        <div>\n                        \t<p>{{title}}</p>\n                        \t<p class=\"font-medium text-sm\">{{subtitle}}</p>\n                        </div>\n                        <svg class=\"w-6 h-6\" fill=\"currentColor\" viewBox=\"0 0 20 20\" xmlns=\"http://www.w3.org/2000/svg\"><path fill-rule=\"evenodd\" d=\"M7.293 14.707a1 1 0 010-1.414L10.586 10 7.293 6.707a1 1 0 011.414-1.414l4 4a1 1 0 010 1.414l-4 4a1 1 0 01-1.414 0z\" clip-rule=\"evenodd\"></path></svg>\n                    </div>\n                </div>\n            </a>\n        {{/each}}\n    </div>\n</div>\n<link href=\"https://unpkg.com/aos@2.3.1/dist/aos.css\" rel=\"stylesheet\">","css":".item:hover .description, .item:focus .description {\n\t@apply opacity-100;\n}","js":"import AOS from 'aos'\nAOS.init()","fields":[{"id":"hrmxk","key":"title","label":"Title","value":"The Maadi Guide","type":"text","fields":[]},{"id":"qayiv","key":"subtitle","label":"Subtitle","value":"The best places to eat in Maadi, Egypt","type":"text","fields":[]},{"id":"jtnwe","key":"items","label":"Items","value":[{"title":"Est ullamcorper","description":"<p>Porta nibh venenatis cras sed felis. Amet mattis vulputate enim nulla aliquet porttitor lacus luctus. Viverra ipsum nunc aliquet bibendum enim. </p>","url":"#","image":{"alt":"mountains","url":"https://images.unsplash.com/photo-1477346611705-65d1883cee1e?ixid=MXwxMjA3fDB8MHxwaG90by1wYWdlfHx8fGVufDB8fHw%3D&ixlib=rb-1.2.1&auto=format&fit=crop&w=1950&q=80","size":null}},{"title":"Tomato","description":"<p>Orci sagittis eu volutpat odio facilisis mauris sit amet. Scelerisque viverra mauris in aliquam sem fringilla ut. Urna condimentum mattis pellentesque id nibh tortor id aliquet.</p>","url":"#","image":{"alt":"Mountains","url":"https://images.unsplash.com/photo-1483728642387-6c3bdd6c93e5?ixid=MXwxMjA3fDB8MHxwaG90by1wYWdlfHx8fGVufDB8fHw%3D&ixlib=rb-1.2.1&auto=format&fit=crop&w=1955&q=80","size":null},"subtitle":"Korean"},{"title":"Nec dui nunc","description":"<p>Viverra ipsum nunc aliquet bibendum enim. Orci sagittis eu volutpat odio facilisis mauris sit amet. Scelerisque viverra mauris in aliquam sem fringilla ut. </p>","url":"#","image":{"alt":"Mountains","url":"https://images.unsplash.com/photo-1506905925346-21bda4d32df4?ixid=MXwxMjA3fDB8MHxwaG90by1wYWdlfHx8fGVufDB8fHw%3D&ixlib=rb-1.2.1&auto=format&fit=crop&w=1950&q=80","size":null}}],"type":"repeater","fields":[{"id":"vxggv","key":"title","label":"Title","value":"","type":"text"},{"id":"mvomp","key":"description","label":"Description","value":"","type":"content"},{"id":"3llpc","key":"url","label":"URL","value":"","type":"url"},{"id":"quqhg","key":"image","label":"Image","value":"","type":"image"},{"id":"lyhoq","key":"subtitle","label":"Subtitle","value":"","type":"text"}]}]},"final":{"html":"<div class=\"bg-white py-8 map\">\n    <div class=\"py-8 text-center text-gray-900 container\">\n        <h3 class=\"text-2xl md:text-3xl font-bold leading-tight\">The Maadi Guide</h3>\n        <p class=\"text-xl\">The best places to eat in Maadi, Egypt</p>\n    </div>\n    <div class=\"grid md:grid-cols-2 lg:grid-cols-3 gap-6 lg:gap-12 pb-16 container\">\n            <a data-aos=\"fade-up\" data-aos-duration=\"1000\" href=\"#\" class=\"item text-white shadow-xl relative pt-8 pb-8 w-full bg-black\">\n            \t\t<img class=\"opacity-50 absolute left-0 top-0 w-full h-full object-cover\" src=\"https://images.unsplash.com/photo-1477346611705-65d1883cee1e?ixid&#x3D;MXwxMjA3fDB8MHxwaG90by1wYWdlfHx8fGVufDB8fHw%3D&amp;ixlib&#x3D;rb-1.2.1&amp;auto&#x3D;format&amp;fit&#x3D;crop&amp;w&#x3D;1950&amp;q&#x3D;80\" alt=\"mountains\">\n                <div class=\"pl-8 pr-4 flex flex-col font-bold leading-tight text-xl relative z-10\">\n            \t\t\t<div class=\"description text-sm font-semibold py-8 opacity-0 transition-opacity duration-200\"><p>Porta nibh venenatis cras sed felis. Amet mattis vulputate enim nulla aliquet porttitor lacus luctus. Viverra ipsum nunc aliquet bibendum enim. </p></div>\n                    <div class=\"flex justify-between\">\n                        <div>\n                        \t<p>Est ullamcorper</p>\n                        \t<p class=\"font-medium text-sm\"></p>\n                        </div>\n                        <svg class=\"w-6 h-6\" fill=\"currentColor\" viewBox=\"0 0 20 20\" xmlns=\"http://www.w3.org/2000/svg\"><path fill-rule=\"evenodd\" d=\"M7.293 14.707a1 1 0 010-1.414L10.586 10 7.293 6.707a1 1 0 011.414-1.414l4 4a1 1 0 010 1.414l-4 4a1 1 0 01-1.414 0z\" clip-rule=\"evenodd\"></path></svg>\n                    </div>\n                </div>\n            </a>\n            <a data-aos=\"fade-up\" data-aos-duration=\"1000\" href=\"#\" class=\"item text-white shadow-xl relative pt-8 pb-8 w-full bg-black\">\n            \t\t<img class=\"opacity-50 absolute left-0 top-0 w-full h-full object-cover\" src=\"https://images.unsplash.com/photo-1483728642387-6c3bdd6c93e5?ixid&#x3D;MXwxMjA3fDB8MHxwaG90by1wYWdlfHx8fGVufDB8fHw%3D&amp;ixlib&#x3D;rb-1.2.1&amp;auto&#x3D;format&amp;fit&#x3D;crop&amp;w&#x3D;1955&amp;q&#x3D;80\" alt=\"Mountains\">\n                <div class=\"pl-8 pr-4 flex flex-col font-bold leading-tight text-xl relative z-10\">\n            \t\t\t<div class=\"description text-sm font-semibold py-8 opacity-0 transition-opacity duration-200\"><p>Orci sagittis eu volutpat odio facilisis mauris sit amet. Scelerisque viverra mauris in aliquam sem fringilla ut. Urna condimentum mattis pellentesque id nibh tortor id aliquet.</p></div>\n                    <div class=\"flex justify-between\">\n                        <div>\n                        \t<p>Tomato</p>\n                        \t<p class=\"font-medium text-sm\">Korean</p>\n                        </div>\n                        <svg class=\"w-6 h-6\" fill=\"currentColor\" viewBox=\"0 0 20 20\" xmlns=\"http://www.w3.org/2000/svg\"><path fill-rule=\"evenodd\" d=\"M7.293 14.707a1 1 0 010-1.414L10.586 10 7.293 6.707a1 1 0 011.414-1.414l4 4a1 1 0 010 1.414l-4 4a1 1 0 01-1.414 0z\" clip-rule=\"evenodd\"></path></svg>\n                    </div>\n                </div>\n            </a>\n            <a data-aos=\"fade-up\" data-aos-duration=\"1000\" href=\"#\" class=\"item text-white shadow-xl relative pt-8 pb-8 w-full bg-black\">\n            \t\t<img class=\"opacity-50 absolute left-0 top-0 w-full h-full object-cover\" src=\"https://images.unsplash.com/photo-1506905925346-21bda4d32df4?ixid&#x3D;MXwxMjA3fDB8MHxwaG90by1wYWdlfHx8fGVufDB8fHw%3D&amp;ixlib&#x3D;rb-1.2.1&amp;auto&#x3D;format&amp;fit&#x3D;crop&amp;w&#x3D;1950&amp;q&#x3D;80\" alt=\"Mountains\">\n                <div class=\"pl-8 pr-4 flex flex-col font-bold leading-tight text-xl relative z-10\">\n            \t\t\t<div class=\"description text-sm font-semibold py-8 opacity-0 transition-opacity duration-200\"><p>Viverra ipsum nunc aliquet bibendum enim. Orci sagittis eu volutpat odio facilisis mauris sit amet. Scelerisque viverra mauris in aliquam sem fringilla ut. </p></div>\n                    <div class=\"flex justify-between\">\n                        <div>\n                        \t<p>Nec dui nunc</p>\n                        \t<p class=\"font-medium text-sm\"></p>\n                        </div>\n                        <svg class=\"w-6 h-6\" fill=\"currentColor\" viewBox=\"0 0 20 20\" xmlns=\"http://www.w3.org/2000/svg\"><path fill-rule=\"evenodd\" d=\"M7.293 14.707a1 1 0 010-1.414L10.586 10 7.293 6.707a1 1 0 011.414-1.414l4 4a1 1 0 010 1.414l-4 4a1 1 0 01-1.414 0z\" clip-rule=\"evenodd\"></path></svg>\n                    </div>\n                </div>\n            </a>\n    </div>\n</div>\n<link href=\"https://unpkg.com/aos@2.3.1/dist/aos.css\" rel=\"stylesheet\">","css":"#component-td4zm .item:hover .description, #component-td4zm .item:focus .description {\n    opacity: 1;\n  }","js":"\n      const primo = {\n        id: '56iti',\n        data: {\"title\":\"The Maadi Guide\",\"subtitle\":\"The best places to eat in Maadi, Egypt\",\"items\":[{\"title\":\"Est ullamcorper\",\"description\":\"<p>Porta nibh venenatis cras sed felis. Amet mattis vulputate enim nulla aliquet porttitor lacus luctus. Viverra ipsum nunc aliquet bibendum enim. </p>\",\"url\":\"#\",\"image\":{\"alt\":\"mountains\",\"url\":\"https://images.unsplash.com/photo-1477346611705-65d1883cee1e?ixid=MXwxMjA3fDB8MHxwaG90by1wYWdlfHx8fGVufDB8fHw%3D&ixlib=rb-1.2.1&auto=format&fit=crop&w=1950&q=80\",\"size\":null}},{\"title\":\"Tomato\",\"description\":\"<p>Orci sagittis eu volutpat odio facilisis mauris sit amet. Scelerisque viverra mauris in aliquam sem fringilla ut. Urna condimentum mattis pellentesque id nibh tortor id aliquet.</p>\",\"url\":\"#\",\"image\":{\"alt\":\"Mountains\",\"url\":\"https://images.unsplash.com/photo-1483728642387-6c3bdd6c93e5?ixid=MXwxMjA3fDB8MHxwaG90by1wYWdlfHx8fGVufDB8fHw%3D&ixlib=rb-1.2.1&auto=format&fit=crop&w=1955&q=80\",\"size\":null},\"subtitle\":\"Korean\"},{\"title\":\"Nec dui nunc\",\"description\":\"<p>Viverra ipsum nunc aliquet bibendum enim. Orci sagittis eu volutpat odio facilisis mauris sit amet. Scelerisque viverra mauris in aliquam sem fringilla ut. </p>\",\"url\":\"#\",\"image\":{\"alt\":\"Mountains\",\"url\":\"https://images.unsplash.com/photo-1506905925346-21bda4d32df4?ixid=MXwxMjA3fDB8MHxwaG90by1wYWdlfHx8fGVufDB8fHw%3D&ixlib=rb-1.2.1&auto=format&fit=crop&w=1950&q=80\",\"size\":null}}],\"id\":\"56iti\"},\n        fields: [{\"id\":\"hrmxk\",\"key\":\"title\",\"label\":\"Title\",\"value\":\"The Maadi Guide\",\"type\":\"text\",\"fields\":[]},{\"id\":\"qayiv\",\"key\":\"subtitle\",\"label\":\"Subtitle\",\"value\":\"The best places to eat in Maadi, Egypt\",\"type\":\"text\",\"fields\":[]},{\"id\":\"jtnwe\",\"key\":\"items\",\"label\":\"Items\",\"value\":[{\"title\":\"Est ullamcorper\",\"description\":\"<p>Porta nibh venenatis cras sed felis. Amet mattis vulputate enim nulla aliquet porttitor lacus luctus. Viverra ipsum nunc aliquet bibendum enim. </p>\",\"url\":\"#\",\"image\":{\"alt\":\"mountains\",\"url\":\"https://images.unsplash.com/photo-1477346611705-65d1883cee1e?ixid=MXwxMjA3fDB8MHxwaG90by1wYWdlfHx8fGVufDB8fHw%3D&ixlib=rb-1.2.1&auto=format&fit=crop&w=1950&q=80\",\"size\":null}},{\"title\":\"Tomato\",\"description\":\"<p>Orci sagittis eu volutpat odio facilisis mauris sit amet. Scelerisque viverra mauris in aliquam sem fringilla ut. Urna condimentum mattis pellentesque id nibh tortor id aliquet.</p>\",\"url\":\"#\",\"image\":{\"alt\":\"Mountains\",\"url\":\"https://images.unsplash.com/photo-1483728642387-6c3bdd6c93e5?ixid=MXwxMjA3fDB8MHxwaG90by1wYWdlfHx8fGVufDB8fHw%3D&ixlib=rb-1.2.1&auto=format&fit=crop&w=1955&q=80\",\"size\":null},\"subtitle\":\"Korean\"},{\"title\":\"Nec dui nunc\",\"description\":\"<p>Viverra ipsum nunc aliquet bibendum enim. Orci sagittis eu volutpat odio facilisis mauris sit amet. Scelerisque viverra mauris in aliquam sem fringilla ut. </p>\",\"url\":\"#\",\"image\":{\"alt\":\"Mountains\",\"url\":\"https://images.unsplash.com/photo-1506905925346-21bda4d32df4?ixid=MXwxMjA3fDB8MHxwaG90by1wYWdlfHx8fGVufDB8fHw%3D&ixlib=rb-1.2.1&auto=format&fit=crop&w=1950&q=80\",\"size\":null}}],\"type\":\"repeater\",\"fields\":[{\"id\":\"vxggv\",\"key\":\"title\",\"label\":\"Title\",\"value\":\"\",\"type\":\"text\"},{\"id\":\"mvomp\",\"key\":\"description\",\"label\":\"Description\",\"value\":\"\",\"type\":\"content\"},{\"id\":\"3llpc\",\"key\":\"url\",\"label\":\"URL\",\"value\":\"\",\"type\":\"url\"},{\"id\":\"quqhg\",\"key\":\"image\",\"label\":\"Image\",\"value\":\"\",\"type\":\"image\"},{\"id\":\"lyhoq\",\"key\":\"subtitle\",\"label\":\"Subtitle\",\"value\":\"\",\"type\":\"text\"}]}]\n      }\n      // turn [import _ from 'lodash'] into [import _ from 'https://cdn.skypack.dev/lodash'];\n      import AOS from 'https://cdn.skypack.dev/aos'\nAOS.init() \n    "}},"title":"Teasers"}]}